INSTALL
LICENSE
setup.py
resources/FreeUniversal-Bold.ttf
resources/FreeUniversal-BoldItalic.ttf
resources/FreeUniversal-Italic.ttf
resources/FreeUniversal-Regular.ttf
src/test/GraphDrawer_Test.py
src/test/MockData.py
src/test/TestWxApplication.py
src/test/zglFTGL_test.py
src/zgl/Quaternion.py
src/zgl/__init__.py
src/zgl/zglAnimation.py
src/zgl/zglApplication.py
src/zgl/zglCamera.py
src/zgl/zglConsole.py
src/zgl/zglDrawer.py
src/zgl/zglFreeType.py
src/zgl/zglPrimitives.py
src/zgl/zglShaders.py
src/zgl/zglText.py
src/zgl/zglUtils.py
src/zgl/zglVertexObject.py
src/zgl/zuiObject.py
src/zgl.egg-info/PKG-INFO
src/zgl.egg-info/SOURCES.txt
src/zgl.egg-info/dependency_links.txt
src/zgl.egg-info/requires.txt
src/zgl.egg-info/top_level.txt
src/zgl_graphdrawer/Edge.py
src/zgl_graphdrawer/EdgePolicy.py
src/zgl_graphdrawer/Event.py
src/zgl_graphdrawer/Frame.py
src/zgl_graphdrawer/GraphDrawerManager.py
src/zgl_graphdrawer/LayoutPolicy.py
src/zgl_graphdrawer/Menu.py
src/zgl_graphdrawer/MouseHandlers.py
src/zgl_graphdrawer/Node.py
src/zgl_graphdrawer/NodePolicy.py
src/zgl_graphdrawer/Port.py
src/zgl_graphdrawer/PortPolicy.py
src/zgl_graphdrawer/Responder.py
src/zgl_graphdrawer/VisualPolicy.py
src/zgl_graphdrawer/__init__.py
src/zgl_graphdrawer/utils.py
src/zgl_graphdrawer/application/__init__.py
src/zgl_graphdrawer/application/wxApplication.py
src/zgl_graphdrawer/canvas/__init__.py
src/zgl_graphdrawer/canvas/gl_canvas.py
src/zgl_graphdrawer/canvas/wx_canvas.py
src/zgl_graphdrawer/canvas/zgl_canvas.py
test/__init__.py