Metadata-Version: 1.0
Name: zgl
Version: 0.1.4
Summary: OpenGL graph drawing library
Home-page: UNKNOWN
Author: zehao chang
Author-email: zehao.chang@gmail.com
License: contact developer
Keywords: OpenGL graph node edge dependency directed
Platform: All
